ml4bio/__init__.py
ml4bio/data.py
ml4bio/ml4bio.py
ml4bio/model.py
ml4bio/model_metrics.py
ml4bio/icons/dt.png
ml4bio/icons/knn.png
ml4bio/icons/lr.png
ml4bio/icons/nb.png
ml4bio/icons/nn.png
ml4bio/icons/none.png
ml4bio/icons/open.png
ml4bio/icons/rf.png
ml4bio/icons/save.png
ml4bio/icons/svm.png
ml4bio-0.1.6.dist-info/LICENSE
ml4bio-0.1.6.dist-info/METADATA
ml4bio-0.1.6.dist-info/WHEEL
ml4bio-0.1.6.dist-info/entry_points.txt
ml4bio-0.1.6.dist-info/top_level.txt
ml4bio-0.1.6.dist-info/RECORD
